S3_Folder_Backup/__init__.py
S3_Folder_Backup/s3_folder_backup.py
s3_folder_backup-1.1.1.dist-info/METADATA
s3_folder_backup-1.1.1.dist-info/WHEEL
s3_folder_backup-1.1.1.dist-info/top_level.txt
s3_folder_backup-1.1.1.dist-info/RECORD
